{
  "warnings": [
    {
      "file": "DetectionKit/DetectionKit.h",
      "line": 12,
      "symbol": "DetectionKitVersionNumber",
      "symbol_kind": "sourcekitten.source.lang.objc.decl.constant",
      "warning": "undocumented"
    },
    {
      "file": "DetectionKit/DetectionKit.h",
      "line": 15,
      "symbol": "DetectionKitVersionString",
      "symbol_kind": "sourcekitten.source.lang.objc.decl.constant",
      "warning": "undocumented"
    }
  ],
  "source_directory": "/Volumes/MacStorage/DetectionKit"
}